Metadata-Version: 1.0
Name: dyaiapi
Version: 0.1
Summary: dyai API Exchange Form
Home-page: http://github.com/jxhno1/dyai-api
Author: zhuc
Author-email: xxxxxxxx@163.com
License: MIT
Platform: UNKNOWN
